norton_beer/__init__.py
norton_beer/apodization.py
norton_beer/ils.py
norton_beer/optimize.py
norton_beer-1.0.1.dist-info/AUTHORS
norton_beer-1.0.1.dist-info/LICENSE
norton_beer-1.0.1.dist-info/METADATA
norton_beer-1.0.1.dist-info/WHEEL
norton_beer-1.0.1.dist-info/top_level.txt
norton_beer-1.0.1.dist-info/RECORD
