Metadata-Version: 2.1
Name: norton-beer
Version: 1.0.1
Summary: norton_beer 1.0.1
Author-email: Konstantin Ntokas <k.ntokas@fz-juelich.de>
License: GNU AFFERO GENERAL PUBLIC LICENSE
Project-URL: repository, https://github.com/konstntokas/norton_beer
Keywords: apodization,norton_beer
Classifier: Programming Language :: Python :: 3
Classifier: License :: OSI Approved :: GNU Affero General Public License v3
Classifier: Operating System :: OS Independent
Requires-Python: >=3.8
License-File: LICENSE
License-File: AUTHORS
Requires-Dist: numpy (>=1.22.0)
Requires-Dist: scipy (>=1.4.1)
